pylops_gpu/LinearOperator.py
pylops_gpu/TorchOperator.py
pylops_gpu/__init__.py
pylops_gpu/version.py
pylops_gpu/avo/__init__.py
pylops_gpu/avo/poststack.py
pylops_gpu/basicoperators/Diagonal.py
pylops_gpu/basicoperators/FirstDerivative.py
pylops_gpu/basicoperators/Identity.py
pylops_gpu/basicoperators/Laplacian.py
pylops_gpu/basicoperators/MatrixMult.py
pylops_gpu/basicoperators/Restriction.py
pylops_gpu/basicoperators/SecondDerivative.py
pylops_gpu/basicoperators/VStack.py
pylops_gpu/basicoperators/__init__.py
pylops_gpu/optimization/__init__.py
pylops_gpu/optimization/cg.py
pylops_gpu/optimization/leastsquares.py
pylops_gpu/optimization/sparsity.py
pylops_gpu/signalprocessing/Convolve1D.py
pylops_gpu/signalprocessing/__init__.py
pylops_gpu/utils/__init__.py
pylops_gpu/utils/backend.py
pylops_gpu/utils/complex.py
pylops_gpu/utils/dottest.py
pylops_gpu/utils/torch2numpy.py
pylops_gpu-0.0.1.dist-info/LICENSE
pylops_gpu-0.0.1.dist-info/METADATA
pylops_gpu-0.0.1.dist-info/WHEEL
pylops_gpu-0.0.1.dist-info/top_level.txt
pylops_gpu-0.0.1.dist-info/zip-safe
pylops_gpu-0.0.1.dist-info/RECORD
