Metadata-Version: 2.1
Name: pylops-gpu
Version: 0.0.1
Summary: An extension to PyLops for linear operators on GPUs.         
Home-page: UNKNOWN
Author: mrava
Author-email: matteoravasi@gmail.com
License: UNKNOWN
Keywords: algebra,inverse problems,large-scale optimization
Platform: UNKNOWN
Classifier: Development Status :: 1 - Planning
Classifier: Intended Audience :: Developers
Classifier: Intended Audience :: Science/Research
Classifier: License :: OSI Approved :: GNU Lesser General Public License v3 or later (LGPLv3+)
Classifier: Natural Language :: English
Classifier: Programming Language :: Python :: 3.6
Classifier: Programming Language :: Python :: 3.7
Classifier: Topic :: Scientific/Engineering :: Mathematics
Requires-Dist: numpy (>=1.15.0)
Requires-Dist: torch (>=1.2.0)
Requires-Dist: pytorch-complex-tensor
Requires-Dist: pylops
